{"coord": {"lon": 44.8014, "lat": 41.6935}, "weather": [{"id": 800, "main": "Clear", "description": "clear sky", "icon": "01n"}], "base": "stations", "main": {"temp": 295.36, "feels_like": 295.1, "temp_min": 295.36, "temp_max": 295.36, "pressure": 1016, "humidity": 56}, "visibility": 10000, "wind": {"speed": 4.12, "deg": 60}, "clouds": {"all": 0}, "dt": 1656958008, "sys": {"type": 1, "id": 8862, "country": "GE", "sunrise": 1656898282, "sunset": 1656952715}, "timezone": 14400, "id": 6324644, "name": "Meria", "cod": 200}